odoo8_addon_crm_lead_supplier-8.0.1.1.0.99.dev19-py3.8-nspkg.pth
odoo_addons/crm_lead_supplier/README.rst
odoo_addons/crm_lead_supplier/__init__.py
odoo_addons/crm_lead_supplier/__openerp__.py
odoo_addons/crm_lead_supplier/i18n/bg.po
odoo_addons/crm_lead_supplier/i18n/ca.po
odoo_addons/crm_lead_supplier/i18n/crm_lead_supplier.pot
odoo_addons/crm_lead_supplier/i18n/de.po
odoo_addons/crm_lead_supplier/i18n/el_GR.po
odoo_addons/crm_lead_supplier/i18n/es.po
odoo_addons/crm_lead_supplier/i18n/fi.po
odoo_addons/crm_lead_supplier/i18n/fr.po
odoo_addons/crm_lead_supplier/i18n/fr_FR.po
odoo_addons/crm_lead_supplier/i18n/hr.po
odoo_addons/crm_lead_supplier/i18n/it.po
odoo_addons/crm_lead_supplier/i18n/nl_NL.po
odoo_addons/crm_lead_supplier/i18n/pt_BR.po
odoo_addons/crm_lead_supplier/i18n/pt_PT.po
odoo_addons/crm_lead_supplier/i18n/sk.po
odoo_addons/crm_lead_supplier/i18n/sl.po
odoo_addons/crm_lead_supplier/i18n/zh_CN.po
odoo_addons/crm_lead_supplier/models/__init__.py
odoo_addons/crm_lead_supplier/models/crm_lead.py
odoo_addons/crm_lead_supplier/static/description/icon.png
odoo_addons/crm_lead_supplier/tests/__init__.py
odoo_addons/crm_lead_supplier/tests/test_lead.py
odoo_addons/crm_lead_supplier/views/crm_lead.xml
odoo8_addon_crm_lead_supplier-8.0.1.1.0.99.dev19.dist-info/METADATA
odoo8_addon_crm_lead_supplier-8.0.1.1.0.99.dev19.dist-info/WHEEL
odoo8_addon_crm_lead_supplier-8.0.1.1.0.99.dev19.dist-info/namespace_packages.txt
odoo8_addon_crm_lead_supplier-8.0.1.1.0.99.dev19.dist-info/top_level.txt
odoo8_addon_crm_lead_supplier-8.0.1.1.0.99.dev19.dist-info/RECORD
